roshverysimplemodule/__init__.py
roshverysimplemodule/add.py
roshverysimplemodule/subtract.py
roshverysimplemodule/extras/__init__.py
roshverysimplemodule/extras/divide.py
roshverysimplemodule/extras/multiply.py
roshverysimplemodule-0.0.3.dist-info/METADATA
roshverysimplemodule-0.0.3.dist-info/WHEEL
roshverysimplemodule-0.0.3.dist-info/top_level.txt
roshverysimplemodule-0.0.3.dist-info/RECORD
