Metadata-Version: 2.1
Name: roshverysimplemodule
Version: 0.0.3
Summary: My first Python package
Home-page: https://github.com/roshanbal
Author: roshan bal
Author-email: <rbal408@gmail.com>
License: UNKNOWN
Keywords: python,first package
Platform: UNKNOWN
Classifier: Development Status :: 3 - Alpha
Classifier: Intended Audience :: Education
Classifier: Programming Language :: Python :: 2
Classifier: Programming Language :: Python :: 3
Classifier: Operating System :: MacOS :: MacOS X
Classifier: Operating System :: Microsoft :: Windows
